LICENSE
powerful_calculator/__init__.py
powerful_calculator/powerful_calculator.py
powerful_calculator-0.1.6.dist-info/entry_points.txt
powerful_calculator-0.1.6.dist-info/LICENSE
powerful_calculator-0.1.6.dist-info/WHEEL
powerful_calculator-0.1.6.dist-info/METADATA
powerful_calculator-0.1.6.dist-info/RECORD
