Metadata-Version: 2.1
Name: powerful-calculator
Version: 0.1.6
Summary: Calculator for basic operation
Home-page: https://github.com/anytokin/calculator
License: MIT
Author: Dawid Konard Kohnke
Author-email: dawid.kohnke.cad@gmail.com
Requires-Python: >=3.7,<4.0
Classifier: License :: OSI Approved :: MIT License
Classifier: Programming Language :: Python :: 3
Classifier: Programming Language :: Python :: 3.10
Classifier: Programming Language :: Python :: 3.7
Classifier: Programming Language :: Python :: 3.8
Classifier: Programming Language :: Python :: 3.9
Project-URL: Repository, https://github.com/anytokin/calculator
